{
  "DocumentConnection": {
    "type": "DocumentConnection",
    "resolveType": "multiCollectionDocumentList",
    "collections": ["pages"]
  },
  "Node": {
    "type": "Node",
    "resolveType": "nodeDocument"
  },
  "DocumentNode": {
    "type": "DocumentNode",
    "resolveType": "multiCollectionDocument",
    "createDocument": "create",
    "updateDocument": "update"
  },
  "PagesBlocks": {
    "type": "PagesBlocks",
    "resolveType": "unionData",
    "typeMap": {
      "navigation": "PagesBlocksNavigation",
      "heroV1": "PagesBlocksHeroV1",
      "heroV2": "PagesBlocksHeroV2",
      "heroV3": "PagesBlocksHeroV3",
      "projects": "PagesBlocksProjects",
      "vision": "PagesBlocksVision",
      "values": "PagesBlocksValues",
      "footer": "PagesBlocksFooter"
    }
  },
  "PagesDocument": {
    "type": "PagesDocument",
    "resolveType": "collectionDocument",
    "collection": "pages",
    "createPagesDocument": "create",
    "updatePagesDocument": "update"
  },
  "PagesConnection": {
    "type": "PagesConnection",
    "resolveType": "collectionDocumentList",
    "collection": "pages"
  }
}
